iams/__init__.py
iams/agent.py
iams/ca.py
iams/constants.py
iams/df.py
iams/exceptions.py
iams/helper.py
iams/runtime.py
iams/server.py
iams/servicer.py
iams/simulation.py
iams/stub.py
iams/aio/__init__.py
iams/aio/grpc.py
iams/aio/influx.py
iams/aio/interfaces.py
iams/aio/manager.py
iams/aio/mqtt.py
iams/aio/opcua.py
iams/aio/tcp.py
iams/aio/zeebe.py
iams/interfaces/__init__.py
iams/interfaces/ca.py
iams/interfaces/channel.py
iams/interfaces/df.py
iams/interfaces/plugin.py
iams/interfaces/runtime.py
iams/interfaces/scheduler.py
iams/interfaces/simulation.py
iams/plugins/arango/__init__.py
iams/plugins/arango/plugin.py
iams/plugins/envoy/__init__.py
iams/plugins/envoy/plugin.py
iams/plugins/fluentd/__init__.py
iams/plugins/fluentd/plugin.py
iams/plugins/influxdb/__init__.py
iams/plugins/influxdb/plugin.py
iams/plugins/mqtt/__init__.py
iams/plugins/mqtt/plugin.py
iams/plugins/sentry/__init__.py
iams/plugins/sentry/plugin.py
iams/plugins/zeebe/__init__.py
iams/plugins/zeebe/plugin.py
iams/proto/__init__.py
iams/proto/agent_pb2.py
iams/proto/agent_pb2_grpc.py
iams/proto/ca_pb2.py
iams/proto/ca_pb2_grpc.py
iams/proto/df_pb2.py
iams/proto/df_pb2_grpc.py
iams/proto/framework_pb2.py
iams/proto/framework_pb2_grpc.py
iams/utils/__init__.py
iams/utils/arangodb.py
iams/utils/grpc.py
iams/utils/outliner.py
iams/utils/plotting.py
iams/utils/plugins.py
iams/utils/scheduler.py
iams/utils/simulation.py
iams/utils/ssl.py
iams-0.7.10.dist-info/LICENSE
iams-0.7.10.dist-info/METADATA
iams-0.7.10.dist-info/WHEEL
iams-0.7.10.dist-info/entry_points.txt
iams-0.7.10.dist-info/top_level.txt
iams-0.7.10.dist-info/RECORD
