Metadata-Version: 2.1
Name: iams
Version: 0.7.10
Summary: An industial agent management system aiming to control agents for manufacturing units.
Home-page: https://github.com/glomium/industrial-ams
Author: Sebastian Braun
Author-email: sebastian.braun@fh-aachen.de
Project-URL: Documentation, https://github.com/glomium/industrial-ams
Project-URL: Source, https://github.com/glomium/industrial-ams
Project-URL: Tracker, https://github.com/glomium/industrial-ams
Classifier: Development Status :: 4 - Beta
Classifier: Intended Audience :: Information Technology
Classifier: Intended Audience :: Manufacturing
Classifier: Intended Audience :: Science/Research
Classifier: License :: OSI Approved :: Mozilla Public License 2.0 (MPL 2.0)
Classifier: Operating System :: OS Independent
Classifier: Programming Language :: Python :: 3 :: Only
Classifier: Programming Language :: Python :: 3.9
Classifier: Programming Language :: Python :: 3.10
Classifier: Programming Language :: Python :: 3.11
Requires-Python: >=3.8
License-File: LICENSE
Requires-Dist: PyYAML ==6.0.1
Requires-Dist: aiohttp[speedups] ==3.8.5
Requires-Dist: cryptography ==41.0.3
Requires-Dist: docker ==6.1.3
Requires-Dist: grpcio-tools
Requires-Dist: grpcio <2,>=1
Requires-Dist: protobuf <5.0dev,>=3.20
